wybthon/__init__.py
wybthon/component.py
wybthon/context.py
wybthon/dev.py
wybthon/dom.py
wybthon/events.py
wybthon/forms.py
wybthon/lazy.py
wybthon/reactivity.py
wybthon/router.py
wybthon/router_core.py
wybthon/vdom.py
wybthon-0.8.0.dist-info/licenses/LICENSE
wybthon-0.8.0.dist-info/METADATA
wybthon-0.8.0.dist-info/WHEEL
wybthon-0.8.0.dist-info/entry_points.txt
wybthon-0.8.0.dist-info/top_level.txt
wybthon-0.8.0.dist-info/RECORD
