Metadata-Version: 2.4
Name: wybthon
Version: 0.8.0
Summary: Client-side Python SPA framework via Pyodide
Author: Owen Carey
License: MIT License
Project-URL: Homepage, https://github.com/wybthon/wybthon
Project-URL: Repository, https://github.com/wybthon/wybthon
Project-URL: Issues, https://github.com/wybthon/wybthon/issues
Project-URL: Changelog, https://github.com/wybthon/wybthon/blob/main/CHANGELOG.md
Classifier: Development Status :: 2 - Pre-Alpha
Classifier: Intended Audience :: Developers
Classifier: License :: OSI Approved :: MIT License
Classifier: Programming Language :: Python :: 3
Classifier: Programming Language :: Python :: 3 :: Only
Classifier: Programming Language :: Python :: 3.9
Classifier: Programming Language :: Python :: 3.10
Classifier: Programming Language :: Python :: 3.11
Classifier: Programming Language :: Python :: 3.12
Classifier: Environment :: WebAssembly
Classifier: Framework :: AsyncIO
Classifier: Topic :: Internet :: WWW/HTTP :: Dynamic Content
Requires-Python: >=3.9
License-File: LICENSE
Provides-Extra: docs
Requires-Dist: mkdocs>=1.5; extra == "docs"
Requires-Dist: mkdocs-material[imaging]>=9.5; extra == "docs"
Requires-Dist: mkdocstrings[python]>=0.24; extra == "docs"
Provides-Extra: dev
Requires-Dist: black>=24.0; extra == "dev"
Requires-Dist: ruff>=0.5; extra == "dev"
Requires-Dist: mypy>=1.10; extra == "dev"
Requires-Dist: pytest>=8.0; extra == "dev"
Requires-Dist: pytest-cov>=4.1; extra == "dev"
Requires-Dist: pytest-playwright>=0.5.0; extra == "dev"
Provides-Extra: ci
Requires-Dist: black>=24.0; extra == "ci"
Requires-Dist: ruff>=0.5; extra == "ci"
Requires-Dist: mypy>=1.10; extra == "ci"
Requires-Dist: pytest>=8.0; extra == "ci"
Requires-Dist: pytest-cov>=4.1; extra == "ci"
Requires-Dist: pytest-playwright>=0.5.0; extra == "ci"
Dynamic: license-file
